wangsu/__init__.py
wangsu/agent/__init__.py
wangsu/agent/models.py
wangsu/alertrules/__init__.py
wangsu/alertrules/models.py
wangsu/appmanage/__init__.py
wangsu/appmanage/models.py
wangsu/authentication/__init__.py
wangsu/authentication/models.py
wangsu/basicmonitor/__init__.py
wangsu/basicmonitor/models.py
wangsu/basicpermission/__init__.py
wangsu/basicpermission/models.py
wangsu/billingsystem/__init__.py
wangsu/billingsystem/models.py
wangsu/cacertificatemanagement/__init__.py
wangsu/cacertificatemanagement/models.py
wangsu/cacherefresh/__init__.py
wangsu/cacherefresh/models.py
wangsu/certificateapplication/__init__.py
wangsu/certificateapplication/models.py
wangsu/certificationmanage/__init__.py
wangsu/certificationmanage/models.py
wangsu/channelsmanagement/__init__.py
wangsu/channelsmanagement/models.py
wangsu/clientsdk/__init__.py
wangsu/clientsdk/models.py
wangsu/cloudtrail/__init__.py
wangsu/cloudtrail/models.py
wangsu/clusterinfor/__init__.py
wangsu/clusterinfor/models.py
wangsu/common/__init__.py
wangsu/common/Constant/Constant.py
wangsu/common/Constant/__init__.py
wangsu/common/auth/AkSkAuth.py
wangsu/common/auth/AkSkConfig.py
wangsu/common/auth/HttpRequestMsg.py
wangsu/common/auth/__init__.py
wangsu/common/exception/ApiAuthException.py
wangsu/common/exception/__init__.py
wangsu/common/util/CryptoUtils.py
wangsu/common/util/HttpUtils.py
wangsu/common/util/__init__.py
wangsu/configcenter/__init__.py
wangsu/configcenter/models.py
wangsu/contentrefresh/__init__.py
wangsu/contentrefresh/models.py
wangsu/contentsercurity/__init__.py
wangsu/contentsercurity/models.py
wangsu/csrmanage/__init__.py
wangsu/csrmanage/models.py
wangsu/customeralarm/__init__.py
wangsu/customeralarm/models.py
wangsu/dataquery/__init__.py
wangsu/dataquery/models.py
wangsu/deploymentmanagement/__init__.py
wangsu/deploymentmanagement/models.py
wangsu/devicemanagement/__init__.py
wangsu/devicemanagement/models.py
wangsu/dnsrecordmanage/__init__.py
wangsu/dnsrecordmanage/models.py
wangsu_sdk_python-1.0.0.dist-info/licenses/LICENSE
wangsu_sdk_python-1.0.0.dist-info/METADATA
wangsu_sdk_python-1.0.0.dist-info/WHEEL
wangsu_sdk_python-1.0.0.dist-info/top_level.txt
wangsu_sdk_python-1.0.0.dist-info/RECORD
